{"trial_id": "01", "hyperparameters": {"space": [{"class_name": "Int", "config": {"name": "units", "default": null, "conditions": [], "min_value": 8, "max_value": 128, "step": 1, "sampling": "linear"}}, {"class_name": "Choice", "config": {"name": "optimizer", "default": "sgd", "conditions": [], "values": ["sgd", "rmsprop", "adam", "adamw", "adadelta", "adagrad", "adamax", "nadam", "ftrl"], "ordered": false}}], "values": {"units": 78, "optimizer": "adam"}}, "metrics": {"metrics": {"loss": {"direction": "min", "observations": [{"value": [0.46114277839660645], "step": 8}]}, "accuracy": {"direction": "max", "observations": [{"value": [0.7687296271324158], "step": 8}]}, "val_loss": {"direction": "min", "observations": [{"value": [0.5086288452148438], "step": 8}]}, "val_accuracy": {"direction": "max", "observations": [{"value": [0.7662337422370911], "step": 8}]}}}, "score": 0.7662337422370911, "best_step": 8, "status": "COMPLETED", "message": null}